LICENSE
README.md
setup.py
python_steamgriddb.egg-info/PKG-INFO
python_steamgriddb.egg-info/SOURCES.txt
python_steamgriddb.egg-info/dependency_links.txt
python_steamgriddb.egg-info/requires.txt
python_steamgriddb.egg-info/top_level.txt
steamgrid/__init__.py
steamgrid/asset.py
steamgrid/author.py
steamgrid/enums.py
steamgrid/game.py
steamgrid/http.py
steamgrid/steamgrid.py