Metadata-Version: 2.1
Name: python-steamgriddb
Version: 1.0.5
Summary: A Python wrapper for SteamGridDB's API
Home-page: https://github.com/ZebcoWeb/python-steamgriddb
Author: Zebco
Author-email: zebco1382@gmail.com
License: MIT
Keywords: steamgriddb,steamgrid,steam,grid,db,api,wrapper
Platform: UNKNOWN
Classifier: Programming Language :: Python :: 3
Classifier: License :: OSI Approved :: MIT License
Classifier: Operating System :: OS Independent
License-File: LICENSE
